<?xml version="1.0" encoding="UTF-8"?><PMML version="4.2" xmlns="http://www.dmg.org/PMML-4_2" xmlns:xsi="http://www.w3.org/2001/XMLSchema-instance" xsi:schemaLocation="http://www.dmg.org/PMML-4_2 http://www.dmg.org/v4-2-1/pmml-4-2.xsd"><Header copyright="(c) Copyright IBM Corp. 2011, 2012" description="randomTrees"><Application name="Analytic-Engine" version="3.0.0.0-131"></Application><Timestamp>Wed Sep 7 9:15:16 2022</Timestamp></Header><DataDictionary numberOfFields="32"><DataField name="Growth_stages" displayName="Growth_stages" optype="categorical" dataType="string"><Extension extender="spss.com" name="flagTypeTrueValue" value="reproductive"></Extension><Value value="reproductive" displayValue="" property="valid"></Value></DataField><DataField name="Perimeter" displayName="Perimeter" optype="continuous" dataType="double"></DataField><DataField name="Extend" displayName="Extend" optype="continuous" dataType="double"></DataField><DataField name="Diameter" displayName="Diameter" optype="continuous" dataType="double"></DataField><DataField name="Area" displayName="Area" optype="continuous" dataType="double"></DataField><DataField name="Circularity_#2" displayName="Circularity_#2" optype="continuous" dataType="double"></DataField><DataField name="Minimum_Ferets_Diameter" displayName="Minimum_Ferets_Diameter" optype="continuous" dataType="double"></DataField><DataField name="Maximum_Ferets_Diameter" displayName="Maximum_Ferets_Diameter" optype="continuous" dataType="double"></DataField><DataField name="Major_Axis" displayName="Major_Axis" optype="continuous" dataType="double"></DataField><DataField name="Minor_Axis" displayName="Minor_Axis" optype="continuous" dataType="double"></DataField><DataField name="Boundary_Size" displayName="Boundary_Size" optype="continuous" dataType="double"></DataField><DataField name="Boxivity" displayName="Boxivity" optype="continuous" dataType="double"></DataField><DataField name="Minimum_projection_area" displayName="Minimum_projection_area" optype="continuous" dataType="double"></DataField><DataField name="Maximum_projection_area" displayName="Maximum_projection_area" optype="continuous" dataType="double"></DataField><DataField name="Polarizability" displayName="Polarizability" optype="continuous" dataType="double"></DataField><DataField name="MaxEStateIndex" displayName="MaxEStateIndex" optype="continuous" dataType="double"></DataField><DataField name="MinEStateIndex" displayName="MinEStateIndex" optype="continuous" dataType="double"></DataField><DataField name="MinAbsEStateIndex" displayName="MinAbsEStateIndex" optype="continuous" dataType="double"></DataField><DataField name="FpDensityMorgan1" displayName="FpDensityMorgan1" optype="continuous" dataType="double"></DataField><DataField name="Kappa1" displayName="Kappa1" optype="continuous" dataType="double"></DataField><DataField name="Kappa3" displayName="Kappa3" optype="continuous" dataType="double"></DataField><DataField name="SlogP_VSA3" displayName="SlogP_VSA3" optype="continuous" dataType="double"></DataField><DataField name="EState_VSA8" displayName="EState_VSA8" optype="continuous" dataType="double"></DataField><DataField name="EState_VSA9" displayName="EState_VSA9" optype="continuous" dataType="double"></DataField><DataField name="MolMR" displayName="MolMR" optype="continuous" dataType="double"></DataField><DataField name="Formation_Energy" displayName="Formation_Energy" optype="continuous" dataType="double"></DataField><DataField name="Count" displayName="Count" optype="continuous" dataType="double"></DataField><DataField name="NP_volume" displayName="NP_volume" optype="continuous" dataType="double"></DataField><DataField name="NP_concentration" displayName="NP_concentration" optype="continuous" dataType="double"></DataField><DataField name="Primary_size" displayName="Primary_size" optype="continuous" dataType="double"></DataField><DataField name="Change_percent" displayName="Change_percent" optype="continuous" dataType="double"></DataField><DataField name="Partition" displayName="Partition" optype="categorical" dataType="string"><Value value="Training" displayValue="Training" property="valid"></Value><Value value="Testing" displayValue="Testing" property="valid"></Value></DataField></DataDictionary><MiningModel functionName="regression"><Extension extender="spss.com" name="modelID" value="scalableRandomTrees_Model"></Extension><MiningSchema><MiningField name="Perimeter" usageType="active" missingValueReplacement="0.0" invalidValueTreatment="asMissing"></MiningField><MiningField name="Diameter" usageType="active" missingValueReplacement="0.0" invalidValueTreatment="asMissing"></MiningField><MiningField name="Area" usageType="active" missingValueReplacement="0.0" invalidValueTreatment="asMissing"></MiningField><MiningField name="Minimum_Ferets_Diameter" usageType="active" missingValueReplacement="0.0" invalidValueTreatment="asMissing"></MiningField><MiningField name="Maximum_Ferets_Diameter" usageType="active" missingValueReplacement="0.0" invalidValueTreatment="asMissing"></MiningField><MiningField name="Major_Axis" usageType="active" missingValueReplacement="0.0" invalidValueTreatment="asMissing"></MiningField><MiningField name="Minor_Axis" usageType="active" missingValueReplacement="0.0" invalidValueTreatment="asMissing"></MiningField><MiningField name="Boundary_Size" usageType="active" missingValueReplacement="0.0" invalidValueTreatment="asMissing"></MiningField><MiningField name="Minimum_projection_area" usageType="active" missingValueReplacement="0.0" invalidValueTreatment="asMissing"></MiningField><MiningField name="Maximum_projection_area" usageType="active" missingValueReplacement="0.0" invalidValueTreatment="asMissing"></MiningField><MiningField name="Polarizability" usageType="active" missingValueReplacement="0.0" invalidValueTreatment="asMissing"></MiningField><MiningField name="MaxEStateIndex" usageType="active" missingValueReplacement="-0.303952992619603" invalidValueTreatment="asMissing"></MiningField><MiningField name="MinEStateIndex" usageType="active" missingValueReplacement="-0.0136866634111803" invalidValueTreatment="asMissing"></MiningField><MiningField name="MinAbsEStateIndex" usageType="active" missingValueReplacement="0.0" invalidValueTreatment="asMissing"></MiningField><MiningField name="FpDensityMorgan1" usageType="active" missingValueReplacement="-0.303952921181458" invalidValueTreatment="asMissing"></MiningField><MiningField name="Kappa1" usageType="active" missingValueReplacement="-0.251778632608595" invalidValueTreatment="asMissing"></MiningField><MiningField name="Kappa3" usageType="active" missingValueReplacement="-0.0156551970089095" invalidValueTreatment="asMissing"></MiningField><MiningField name="SlogP_VSA3" usageType="active" missingValueReplacement="-0.279264798511116" invalidValueTreatment="asMissing"></MiningField><MiningField name="EState_VSA8" usageType="active" missingValueReplacement="2.09659857999873E-4" invalidValueTreatment="asMissing"></MiningField><MiningField name="EState_VSA9" usageType="active" missingValueReplacement="-0.240863520558741" invalidValueTreatment="asMissing"></MiningField><MiningField name="MolMR" usageType="active" missingValueReplacement="0.0" invalidValueTreatment="asMissing"></MiningField><MiningField name="Count" usageType="active" missingValueReplacement="0.0" invalidValueTreatment="asMissing"></MiningField><MiningField name="NP_volume" usageType="active" missingValueReplacement="-0.238513248359329" invalidValueTreatment="asMissing"></MiningField><MiningField name="NP_concentration" usageType="active" missingValueReplacement="0.0" invalidValueTreatment="asMissing"></MiningField><MiningField name="Primary_size" usageType="active" missingValueReplacement="-0.0304878048780487" invalidValueTreatment="asMissing"></MiningField><MiningField name="Change_percent" usageType="predicted" invalidValueTreatment="asMissing"></MiningField></MiningSchema><Segmentation multipleModelMethod="average"><Segment id="1"><True></True><TreeModel functionName="regression" splitCharacteristic="binarySplit"><MiningSchema><MiningField name="Perimeter" usageType="active" missingValueReplacement="0.0" invalidValueTreatment="asMissing"></MiningField><MiningField name="Maximum_Ferets_Diameter" usageType="active" missingValueReplacement="0.0" invalidValueTreatment="asMissing"></MiningField><MiningField name="MaxEStateIndex" usageType="active" missingValueReplacement="-0.303952992619603" invalidValueTreatment="asMissing"></MiningField><MiningField name="MinAbsEStateIndex" usageType="active" missingValueReplacement="0.0" invalidValueTreatment="asMissing"></MiningField><MiningField name="EState_VSA8" usageType="active" missingValueReplacement="2.09659857999873E-4" invalidValueTreatment="asMissing"></MiningField><MiningField name="Count" usageType="active" missingValueReplacement="0.0" invalidValueTreatment="asMissing"></MiningField><MiningField name="NP_concentration" usageType="active" missingValueReplacement="0.0" invalidValueTreatment="asMissing"></MiningField><MiningField name="Change_percent" usageType="predicted" invalidValueTreatment="asMissing"></MiningField></MiningSchema><Node id="1"><True></True><Node id="2"><SimplePredicate field="Perimeter" operator="lessOrEqual" value="0.506637832642518"></SimplePredicate><Node id="4"><SimplePredicate field="MinAbsEStateIndex" operator="lessOrEqual" value="0.0"></SimplePredicate><Node id="8"><SimplePredicate field="Maximum_Ferets_Diameter" operator="lessOrEqual" value="0.111961337092227"></SimplePredicate><Node id="16"><SimplePredicate field="NP_concentration" operator="lessOrEqual" value="5.625"></SimplePredicate><Node id="32"><SimplePredicate field="EState_VSA8" operator="lessOrEqual" value="0.0"></SimplePredicate><Node id="64" score="0.0275"><SimplePredicate field="MaxEStateIndex" operator="lessOrEqual" value="-0.305039565498522"></SimplePredicate></Node><Node id="65"><True></True><Node id="130" score="0.024285714285714282"><SimplePredicate field="NP_concentration" operator="lessOrEqual" value="-0.5"></SimplePredicate></Node><Node id="131" score="0.016666666666666666"><True></True></Node></Node></Node><Node id="33" score="0.06"><True></True></Node></Node><Node id="17" score="0.12000000000000001"><True></True></Node></Node><Node id="9"><True></True><Node id="18" score="-0.04"><SimplePredicate field="MaxEStateIndex" operator="lessOrEqual" value="-0.392843385504398"></SimplePredicate></Node><Node id="19" score="0.002"><True></True></Node></Node></Node><Node id="5"><True></True><Node id="10" score="0.14333333333333334"><SimplePredicate field="Count" operator="lessOrEqual" value="0.378375208468711"></SimplePredicate></Node><Node id="11" score="0.21800000000000003"><True></True></Node></Node></Node><Node id="3" score="-0.7209999999999999"><True></True></Node></Node></TreeModel></Segment><Segment id="2"><True></True><TreeModel functionName="regression" splitCharacteristic="binarySplit"><MiningSchema><MiningField name="Perimeter" usageType="active" missingValueReplacement="0.0" invalidValueTreatment="asMissing"></MiningField><MiningField name="Diameter" usageType="active" missingValueReplacement="0.0" invalidValueTreatment="asMissing"></MiningField><MiningField name="Area" usageType="active" missingValueReplacement="0.0" invalidValueTreatment="asMissing"></MiningField><MiningField name="MaxEStateIndex" usageType="active" missingValueReplacement="-0.303952992619603" invalidValueTreatment="asMissing"></MiningField><MiningField name="MinAbsEStateIndex" usageType="active" missingValueReplacement="0.0" invalidValueTreatment="asMissing"></MiningField><MiningField name="FpDensityMorgan1" usageType="active" missingValueReplacement="-0.303952921181458" invalidValueTreatment="asMissing"></MiningField><MiningField name="NP_concentration" usageType="active" missingValueReplacement="0.0" invalidValueTreatment="asMissing"></MiningField><MiningField name="Change_percent" usageType="predicted" invalidValueTreatment="asMissing"></MiningField></MiningSchema><Node id="1"><True></True><Node id="2"><SimplePredicate field="Perimeter" operator="lessOrEqual" value="0.506637832642518"></SimplePredicate><Node id="4"><SimplePredicate field="MinAbsEStateIndex" operator="lessOrEqual" value="0.0"></SimplePredicate><Node id="8"><SimplePredicate field="Area" operator="lessOrEqual" value="0.0629774310586653"></SimplePredicate><Node id="16" score="0.0475"><SimplePredicate field="MaxEStateIndex" operator="lessOrEqual" value="-0.392843385504398"></SimplePredicate></Node><Node id="17"><True></True><Node id="34"><SimplePredicate field="NP_concentration" operator="lessOrEqual" value="0.625"></SimplePredicate><Node id="68"><SimplePredicate field="Diameter" operator="lessOrEqual" value="-0.674749316317229"></SimplePredicate><Node id="136"><SimplePredicate field="NP_concentration" operator="lessOrEqual" value="-0.5"></SimplePredicate><Node id="272" score="0.017499999999999998"><SimplePredicate field="NP_concentration" operator="lessOrEqual" value="-0.5625"></SimplePredicate></Node><Node id="273" score="0.02"><True></True></Node></Node><Node id="137" score="0.013333333333333334"><True></True></Node></Node><Node id="69" score="-0.01"><True></True></Node></Node><Node id="35" score="0.025"><True></True></Node></Node></Node><Node id="9"><True></True><Node id="18" score="-0.05333333333333334"><SimplePredicate field="FpDensityMorgan1" operator="lessOrEqual" value="-0.394335168678464"></SimplePredicate></Node><Node id="19" score="0.008"><True></True></Node></Node></Node><Node id="5" score="0.142"><True></True></Node></Node><Node id="3"><True></True><Node id="6" score="-0.274"><SimplePredicate field="NP_concentration" operator="lessOrEqual" value="0.0"></SimplePredicate></Node><Node id="7" score="-0.98"><True></True></Node></Node></Node></TreeModel></Segment><Segment id="3"><True></True><TreeModel functionName="regression" splitCharacteristic="binarySplit"><MiningSchema><MiningField name="Perimeter" usageType="active" missingValueReplacement="0.0" invalidValueTreatment="asMissing"></MiningField><MiningField name="Area" usageType="active" missingValueReplacement="0.0" invalidValueTreatment="asMissing"></MiningField><MiningField name="Boundary_Size" usageType="active" missingValueReplacement="0.0" invalidValueTreatment="asMissing"></MiningField><MiningField name="MinEStateIndex" usageType="active" missingValueReplacement="-0.0136866634111803" invalidValueTreatment="asMissing"></MiningField><MiningField name="FpDensityMorgan1" usageType="active" missingValueReplacement="-0.303952921181458" invalidValueTreatment="asMissing"></MiningField><MiningField name="Kappa3" usageType="active" missingValueReplacement="-0.0156551970089095" invalidValueTreatment="asMissing"></MiningField><MiningField name="Count" usageType="active" missingValueReplacement="0.0" invalidValueTreatment="asMissing"></MiningField><MiningField name="Change_percent" usageType="predicted" invalidValueTreatment="asMissing"></MiningField></MiningSchema><Node id="1"><True></True><Node id="2"><SimplePredicate field="Area" operator="lessOrEqual" value="0.557919608047695"></SimplePredicate><Node id="4"><SimplePredicate field="Count" operator="lessOrEqual" value="0.378375208468711"></SimplePredicate><Node id="8" score="-0.105"><SimplePredicate field="Boundary_Size" operator="lessOrEqual" value="-0.51320239334027"></SimplePredicate></Node><Node id="9"><True></True><Node id="18" score="-0.08"><SimplePredicate field="Kappa3" operator="lessOrEqual" value="-0.22213430744409"></SimplePredicate></Node><Node id="19"><True></True><Node id="38"><SimplePredicate field="Perimeter" operator="lessOrEqual" value="0.461104102841352"></SimplePredicate><Node id="76"><SimplePredicate field="FpDensityMorgan1" operator="lessOrEqual" value="-0.303952921181458"></SimplePredicate><Node id="152" score="0.005"><SimplePredicate field="FpDensityMorgan1" operator="lessOrEqual" value="-0.347592490068806"></SimplePredicate></Node><Node id="153"><True></True><Node id="306" score="0.03"><SimplePredicate field="MinEStateIndex" operator="lessOrEqual" value="-0.0137355717293702"></SimplePredicate></Node><Node id="307" score="0.014285714285714287"><True></True></Node></Node></Node><Node id="77" score="0.045000000000000005"><True></True></Node></Node><Node id="39" score="0.16"><True></True></Node></Node></Node></Node><Node id="5" score="0.22142857142857147"><True></True></Node></Node><Node id="3" score="-0.688"><True></True></Node></Node></TreeModel></Segment><Segment id="4"><True></True><TreeModel functionName="regression" splitCharacteristic="binarySplit"><MiningSchema><MiningField name="Diameter" usageType="active" missingValueReplacement="0.0" invalidValueTreatment="asMissing"></MiningField><MiningField name="Area" usageType="active" missingValueReplacement="0.0" invalidValueTreatment="asMissing"></MiningField><MiningField name="Count" usageType="active" missingValueReplacement="0.0" invalidValueTreatment="asMissing"></MiningField><MiningField name="NP_concentration" usageType="active" missingValueReplacement="0.0" invalidValueTreatment="asMissing"></MiningField><MiningField name="Change_percent" usageType="predicted" invalidValueTreatment="asMissing"></MiningField></MiningSchema><Node id="1"><True></True><Node id="2"><SimplePredicate field="Area" operator="lessOrEqual" value="0.557919608047695"></SimplePredicate><Node id="4"><SimplePredicate field="Count" operator="lessOrEqual" value="0.0"></SimplePredicate><Node id="8"><SimplePredicate field="Area" operator="lessOrEqual" value="0.0629774310586653"></SimplePredicate><Node id="16"><SimplePredicate field="NP_concentration" operator="lessOrEqual" value="5.625"></SimplePredicate><Node id="32"><SimplePredicate field="NP_concentration" operator="lessOrEqual" value="0.625"></SimplePredicate><Node id="64" score="0.015"><SimplePredicate field="Diameter" operator="lessOrEqual" value="0.0"></SimplePredicate></Node><Node id="65" score="-0.01"><True></True></Node></Node><Node id="33" score="0.06"><True></True></Node></Node><Node id="17" score="0.12000000000000001"><True></True></Node></Node><Node id="9" score="-0.046"><True></True></Node></Node><Node id="5"><True></True><Node id="10" score="0.13"><SimplePredicate field="Area" operator="lessOrEqual" value="-0.455909229657621"></SimplePredicate></Node><Node id="11" score="0.18000000000000002"><True></True></Node></Node></Node><Node id="3" score="-0.5666666666666667"><True></True></Node></Node></TreeModel></Segment><Segment id="5"><True></True><TreeModel functionName="regression" splitCharacteristic="binarySplit"><MiningSchema><MiningField name="Perimeter" usageType="active" missingValueReplacement="0.0" invalidValueTreatment="asMissing"></MiningField><MiningField name="Diameter" usageType="active" missingValueReplacement="0.0" invalidValueTreatment="asMissing"></MiningField><MiningField name="Major_Axis" usageType="active" missingValueReplacement="0.0" invalidValueTreatment="asMissing"></MiningField><MiningField name="MinEStateIndex" usageType="active" missingValueReplacement="-0.0136866634111803" invalidValueTreatment="asMissing"></MiningField><MiningField name="NP_concentration" usageType="active" missingValueReplacement="0.0" invalidValueTreatment="asMissing"></MiningField><MiningField name="Change_percent" usageType="predicted" invalidValueTreatment="asMissing"></MiningField></MiningSchema><Node id="1"><True></True><Node id="2"><SimplePredicate field="Major_Axis" operator="lessOrEqual" value="0.438375927452596"></SimplePredicate><Node id="4" score="0.3"><SimplePredicate field="Perimeter" operator="lessOrEqual" value="-0.906049137982819"></SimplePredicate></Node><Node id="5"><True></True><Node id="10" score="0.088"><SimplePredicate field="Perimeter" operator="lessOrEqual" value="-0.538895897158647"></SimplePredicate></Node><Node id="11"><True></True><Node id="22"><SimplePredicate field="Diameter" operator="lessOrEqual" value="0.017137648131267"></SimplePredicate><Node id="44" score="0.03833333333333332"><SimplePredicate field="MinEStateIndex" operator="lessOrEqual" value="-0.0137355717293702"></SimplePredicate></Node><Node id="45"><True></True><Node id="90"><SimplePredicate field="NP_concentration" operator="lessOrEqual" value="5.625"></SimplePredicate><Node id="180" score="0.016"><SimplePredicate field="Perimeter" operator="lessOrEqual" value="-0.498828617768967"></SimplePredicate></Node><Node id="181" score="0.007999999999999998"><True></True></Node></Node><Node id="91" score="0.1"><True></True></Node></Node></Node><Node id="23" score="-0.033999999999999996"><True></True></Node></Node></Node></Node><Node id="3" score="-0.625"><True></True></Node></Node></TreeModel></Segment><Segment id="6"><True></True><TreeModel functionName="regression" splitCharacteristic="binarySplit"><MiningSchema><MiningField name="Perimeter" usageType="active" missingValueReplacement="0.0" invalidValueTreatment="asMissing"></MiningField><MiningField name="Diameter" usageType="active" missingValueReplacement="0.0" invalidValueTreatment="asMissing"></MiningField><MiningField name="MaxEStateIndex" usageType="active" missingValueReplacement="-0.303952992619603" invalidValueTreatment="asMissing"></MiningField><MiningField name="MinEStateIndex" usageType="active" missingValueReplacement="-0.0136866634111803" invalidValueTreatment="asMissing"></MiningField><MiningField name="NP_concentration" usageType="active" missingValueReplacement="0.0" invalidValueTreatment="asMissing"></MiningField><MiningField name="Change_percent" usageType="predicted" invalidValueTreatment="asMissing"></MiningField></MiningSchema><Node id="1"><True></True><Node id="2"><SimplePredicate field="Perimeter" operator="lessOrEqual" value="0.506637832642518"></SimplePredicate><Node id="4"><SimplePredicate field="MaxEStateIndex" operator="lessOrEqual" value="0.486770160437491"></SimplePredicate><Node id="8"><SimplePredicate field="Diameter" operator="lessOrEqual" value="0.325250683682771"></SimplePredicate><Node id="16"><SimplePredicate field="NP_concentration" operator="lessOrEqual" value="-0.5625"></SimplePredicate><Node id="32" score="-0.08666666666666667"><SimplePredicate field="Perimeter" operator="lessOrEqual" value="-0.538895897158647"></SimplePredicate></Node><Node id="33" score="0.017499999999999998"><True></True></Node></Node><Node id="17"><True></True><Node id="34"><SimplePredicate field="MinEStateIndex" operator="lessOrEqual" value="0.0"></SimplePredicate><Node id="68"><SimplePredicate field="Diameter" operator="lessOrEqual" value="0.0"></SimplePredicate><Node id="136" score="0.02076923076923077"><SimplePredicate field="Perimeter" operator="lessOrEqual" value="-0.498828617768967"></SimplePredicate></Node><Node id="137" score="0.06"><True></True></Node></Node><Node id="69" score="-0.015000000000000001"><True></True></Node></Node><Node id="35" score="0.2"><True></True></Node></Node></Node><Node id="9" score="0.16"><True></True></Node></Node><Node id="5" score="0.1975"><True></True></Node></Node><Node id="3"><True></True><Node id="6" score="-0.36"><SimplePredicate field="NP_concentration" operator="lessOrEqual" value="0.625"></SimplePredicate></Node><Node id="7" score="-0.9775"><True></True></Node></Node></Node></TreeModel></Segment><Segment id="7"><True></True><TreeModel functionName="regression" splitCharacteristic="binarySplit"><MiningSchema><MiningField name="Perimeter" usageType="active" missingValueReplacement="0.0" invalidValueTreatment="asMissing"></MiningField><MiningField name="Maximum_Ferets_Diameter" usageType="active" missingValueReplacement="0.0" invalidValueTreatment="asMissing"></MiningField><MiningField name="Boundary_Size" usageType="active" missingValueReplacement="0.0" invalidValueTreatment="asMissing"></MiningField><MiningField name="MaxEStateIndex" usageType="active" missingValueReplacement="-0.303952992619603" invalidValueTreatment="asMissing"></MiningField><MiningField name="MinEStateIndex" usageType="active" missingValueReplacement="-0.0136866634111803" invalidValueTreatment="asMissing"></MiningField><MiningField name="Kappa1" usageType="active" missingValueReplacement="-0.251778632608595" invalidValueTreatment="asMissing"></MiningField><MiningField name="NP_concentration" usageType="active" missingValueReplacement="0.0" invalidValueTreatment="asMissing"></MiningField><MiningField name="Change_percent" usageType="predicted" invalidValueTreatment="asMissing"></MiningField></MiningSchema><Node id="1"><True></True><Node id="2"><SimplePredicate field="MinEStateIndex" operator="lessOrEqual" value="0.986264428270629"></SimplePredicate><Node id="4" score="0.2225"><SimplePredicate field="Perimeter" operator="lessOrEqual" value="-0.906049137982819"></SimplePredicate></Node><Node id="5"><True></True><Node id="10"><SimplePredicate field="Boundary_Size" operator="lessOrEqual" value="0.486797606659729"></SimplePredicate><Node id="20"><SimplePredicate field="Maximum_Ferets_Diameter" operator="lessOrEqual" value="0.111961337092227"></SimplePredicate><Node id="40" score="0.0675"><SimplePredicate field="Kappa1" operator="lessOrEqual" value="-0.386917877370919"></SimplePredicate></Node><Node id="41"><True></True><Node id="82" score="-0.075"><SimplePredicate field="NP_concentration" operator="lessOrEqual" value="-0.5625"></SimplePredicate></Node><Node id="83"><True></True><Node id="166"><SimplePredicate field="Kappa1" operator="lessOrEqual" value="0.0"></SimplePredicate><Node id="332"><SimplePredicate field="NP_concentration" operator="lessOrEqual" value="5.625"></SimplePredicate><Node id="664" score="0.03"><SimplePredicate field="Kappa1" operator="lessOrEqual" value="-0.305371361866381"></SimplePredicate></Node><Node id="665" score="0.01"><True></True></Node></Node><Node id="333" score="0.1"><True></True></Node></Node><Node id="167" score="0.24"><True></True></Node></Node></Node></Node><Node id="21"><True></True><Node id="42" score="-0.08"><SimplePredicate field="MaxEStateIndex" operator="lessOrEqual" value="-0.392843385504398"></SimplePredicate></Node><Node id="43" score="0.005"><True></True></Node></Node></Node><Node id="11" score="0.16"><True></True></Node></Node></Node><Node id="3" score="-0.7749999999999999"><True></True></Node></Node></TreeModel></Segment><Segment id="8"><True></True><TreeModel functionName="regression" splitCharacteristic="binarySplit"><MiningSchema><MiningField name="Perimeter" usageType="active" missingValueReplacement="0.0" invalidValueTreatment="asMissing"></MiningField><MiningField name="Diameter" usageType="active" missingValueReplacement="0.0" invalidValueTreatment="asMissing"></MiningField><MiningField name="Area" usageType="active" missingValueReplacement="0.0" invalidValueTreatment="asMissing"></MiningField><MiningField name="Minimum_Ferets_Diameter" usageType="active" missingValueReplacement="0.0" invalidValueTreatment="asMissing"></MiningField><MiningField name="Maximum_projection_area" usageType="active" missingValueReplacement="0.0" invalidValueTreatment="asMissing"></MiningField><MiningField name="MinEStateIndex" usageType="active" missingValueReplacement="-0.0136866634111803" invalidValueTreatment="asMissing"></MiningField><MiningField name="MinAbsEStateIndex" usageType="active" missingValueReplacement="0.0" invalidValueTreatment="asMissing"></MiningField><MiningField name="Count" usageType="active" missingValueReplacement="0.0" invalidValueTreatment="asMissing"></MiningField><MiningField name="NP_concentration" usageType="active" missingValueReplacement="0.0" invalidValueTreatment="asMissing"></MiningField><MiningField name="Change_percent" usageType="predicted" invalidValueTreatment="asMissing"></MiningField></MiningSchema><Node id="1"><True></True><Node id="2"><SimplePredicate field="Minimum_Ferets_Diameter" operator="lessOrEqual" value="0.724654647623507"></SimplePredicate><Node id="4"><SimplePredicate field="Maximum_projection_area" operator="lessOrEqual" value="0.0"></SimplePredicate><Node id="8"><SimplePredicate field="Count" operator="lessOrEqual" value="0.0"></SimplePredicate><Node id="16"><SimplePredicate field="Perimeter" operator="lessOrEqual" value="0.227668649005826"></SimplePredicate><Node id="32"><SimplePredicate field="Diameter" operator="lessOrEqual" value="-0.674749316317229"></SimplePredicate><Node id="64" score="0.0275"><SimplePredicate field="MinEStateIndex" operator="lessOrEqual" value="-0.0137355717293702"></SimplePredicate></Node><Node id="65"><True></True><Node id="130" score="0.011666666666666667"><SimplePredicate field="NP_concentration" operator="lessOrEqual" value="-0.125"></SimplePredicate></Node><Node id="131" score="0.02"><True></True></Node></Node></Node><Node id="33" score="0.054000000000000006"><True></True></Node></Node><Node id="17"><True></True><Node id="34" score="-0.06"><SimplePredicate field="MinAbsEStateIndex" operator="lessOrEqual" value="-0.016600624536552"></SimplePredicate></Node><Node id="35" score="0.005"><True></True></Node></Node></Node><Node id="9" score="0.16"><True></True></Node></Node><Node id="5"><True></True><Node id="10" score="0.06"><SimplePredicate field="NP_concentration" operator="lessOrEqual" value="-0.5625"></SimplePredicate></Node><Node id="11"><True></True><Node id="22" score="0.24636363636363637"><SimplePredicate field="Area" operator="lessOrEqual" value="-0.455909229657621"></SimplePredicate></Node><Node id="23" score="0.21428571428571427"><True></True></Node></Node></Node></Node><Node id="3" score="-0.485"><True></True></Node></Node></TreeModel></Segment><Segment id="9"><True></True><TreeModel functionName="regression" splitCharacteristic="binarySplit"><MiningSchema><MiningField name="Perimeter" usageType="active" missingValueReplacement="0.0" invalidValueTreatment="asMissing"></MiningField><MiningField name="Diameter" usageType="active" missingValueReplacement="0.0" invalidValueTreatment="asMissing"></MiningField><MiningField name="Area" usageType="active" missingValueReplacement="0.0" invalidValueTreatment="asMissing"></MiningField><MiningField name="MinAbsEStateIndex" usageType="active" missingValueReplacement="0.0" invalidValueTreatment="asMissing"></MiningField><MiningField name="Count" usageType="active" missingValueReplacement="0.0" invalidValueTreatment="asMissing"></MiningField><MiningField name="NP_volume" usageType="active" missingValueReplacement="-0.238513248359329" invalidValueTreatment="asMissing"></MiningField><MiningField name="NP_concentration" usageType="active" missingValueReplacement="0.0" invalidValueTreatment="asMissing"></MiningField><MiningField name="Change_percent" usageType="predicted" invalidValueTreatment="asMissing"></MiningField></MiningSchema><Node id="1"><True></True><Node id="2"><SimplePredicate field="Area" operator="lessOrEqual" value="0.557919608047695"></SimplePredicate><Node id="4"><SimplePredicate field="NP_volume" operator="lessOrEqual" value="0.546667280949791"></SimplePredicate><Node id="8"><SimplePredicate field="MinAbsEStateIndex" operator="lessOrEqual" value="-0.0136873328356098"></SimplePredicate><Node id="16"><SimplePredicate field="Perimeter" operator="lessOrEqual" value="0.0"></SimplePredicate><Node id="32"><SimplePredicate field="NP_concentration" operator="lessOrEqual" value="0.625"></SimplePredicate><Node id="64"><SimplePredicate field="Diameter" operator="lessOrEqual" value="-0.674749316317229"></SimplePredicate><Node id="128" score="0.02"><SimplePredicate field="NP_concentration" operator="lessOrEqual" value="-0.5"></SimplePredicate></Node><Node id="129" score="0.016666666666666666"><True></True></Node></Node><Node id="65" score="0.01"><True></True></Node></Node><Node id="33" score="0.14"><True></True></Node></Node><Node id="17" score="-0.048"><True></True></Node></Node><Node id="9"><True></True><Node id="18"><SimplePredicate field="Count" operator="lessOrEqual" value="0.0"></SimplePredicate><Node id="36" score="0.021111111111111112"><SimplePredicate field="NP_concentration" operator="lessOrEqual" value="5.625"></SimplePredicate></Node><Node id="37" score="0.1"><True></True></Node></Node><Node id="19"><True></True><Node id="38" score="0.08"><SimplePredicate field="Perimeter" operator="lessOrEqual" value="-0.538895897158647"></SimplePredicate></Node><Node id="39" score="0.16"><True></True></Node></Node></Node></Node><Node id="5" score="0.18"><True></True></Node></Node><Node id="3" score="-0.6516666666666666"><True></True></Node></Node></TreeModel></Segment></Segmentation></MiningModel></PMML>